clinker/__init__.py
clinker/align.py
clinker/classes.py
clinker/formatters.py
clinker/main.py
clinker/plot.py
clinker/plot/clinker.js
clinker/plot/clustermap.min.js
clinker/plot/d3.min.js
clinker/plot/index.html
clinker/plot/mock.json
clinker/plot/style.css
clinker_windows-0.0.29.dist-info/LICENSE
clinker_windows-0.0.29.dist-info/METADATA
clinker_windows-0.0.29.dist-info/WHEEL
clinker_windows-0.0.29.dist-info/entry_points.txt
clinker_windows-0.0.29.dist-info/top_level.txt
clinker_windows-0.0.29.dist-info/RECORD
