Metadata-Version: 2.1
Name: clinker-windows
Version: 0.0.29
Home-page: https://github.com/xianyu-123/clinker-windows
Author: Cameron Gilchrist
Classifier: Programming Language :: Python :: 3
Classifier: License :: OSI Approved :: MIT License
Classifier: Operating System :: OS Independent
Requires-Python: >=3.6
License-File: LICENSE
Requires-Dist: biopython (>=1.78)
Requires-Dist: numpy (>=1.13.3)
Requires-Dist: scipy (>=1.3.3)
Requires-Dist: disjoint-set (>=0.7.1)
Requires-Dist: gffutils
